Metadata-Version: 1.0
Name: altugstestpackage
Version: 0.1.1
Summary: A Python package example
Home-page: https://altugb@bitbucket.org/altugb/testpackage.git
Author: altugb
Author-email: altug.bitlislioglu@epfl.ch
License: UNKNOWN
Platform: UNKNOWN
